grader/__init__.py
grader/__main__.py
autograde.py-0.0.2.dist-info/LICENSE
autograde.py-0.0.2.dist-info/METADATA
autograde.py-0.0.2.dist-info/WHEEL
autograde.py-0.0.2.dist-info/top_level.txt
autograde.py-0.0.2.dist-info/RECORD
